okt.py
commands/__init__.py
commands/config.py
commands/users.py
okt-0.0.3.dist-info/LICENSE
okt-0.0.3.dist-info/METADATA
okt-0.0.3.dist-info/WHEEL
okt-0.0.3.dist-info/entry_points.txt
okt-0.0.3.dist-info/top_level.txt
okt-0.0.3.dist-info/RECORD
